pixelpuzzle/__init__.py
pixelpuzzle/__main__.py
pixelpuzzle/core.py
pixelpuzzle-1.0.5.dist-info/licenses/LICENSE
pixelpuzzle-1.0.5.dist-info/METADATA
pixelpuzzle-1.0.5.dist-info/WHEEL
pixelpuzzle-1.0.5.dist-info/entry_points.txt
pixelpuzzle-1.0.5.dist-info/top_level.txt
pixelpuzzle-1.0.5.dist-info/RECORD
