Metadata-Version: 2.4
Name: pixelpuzzle
Version: 1.0.5
Summary: Encode/decode images using Base64 or shuffle/recover the pixels of images.
Author-email: Zhan Ziyuan <ziyuanzhan@mail.nankai.edu.cn>
Maintainer-email: Zhan Ziyuan <ziyuanzhan@mail.nankai.edu.cn>
License: GNU GPLv3
Project-URL: Homepage, https://github.com/ZhanZiyuan/PixelPuzzle
Project-URL: Bug Tracker, https://github.com/ZhanZiyuan/PixelPuzzle/issues
Classifier: Environment :: Console
Classifier: License :: OSI Approved :: GNU General Public License v3 (GPLv3)
Classifier: Operating System :: Microsoft :: Windows
Classifier: Operating System :: POSIX :: Linux
Classifier: Programming Language :: Python :: 3.10
Classifier: Programming Language :: Python :: 3.11
Classifier: Programming Language :: Python :: 3.12
Classifier: Programming Language :: Python :: 3.13
Classifier: Topic :: Multimedia :: Graphics
Classifier: Topic :: Security :: Cryptography
Requires-Python: >=3.10
License-File: LICENSE
Requires-Dist: numpy>=2.2.4
Requires-Dist: pillow>=11.1.0
Dynamic: license-file
